doppyo/__init__.py
doppyo/diagnostic.py
doppyo/skill.py
doppyo/sugar.py
doppyo/utils.py
doppyo/test/__init__.py
doppyo/test/test_utils.py
doppyo-0.0.2.dist-info/DESCRIPTION.rst
doppyo-0.0.2.dist-info/METADATA
doppyo-0.0.2.dist-info/RECORD
doppyo-0.0.2.dist-info/WHEEL
doppyo-0.0.2.dist-info/metadata.json
doppyo-0.0.2.dist-info/top_level.txt
