Metadata-Version: 2.0
Name: doppyo
Version: 0.0.2
Summary: Diagnostics and verification package
Home-page: https://github.com/csiro-dcfp/doppyo
Author: Dougie Squire
Author-email: dougie.squire@csiro.au
License: UNKNOWN
Platform: UNKNOWN
Classifier: Programming Language :: Python :: 3
Classifier: License :: OSI Approved :: MIT License
Classifier: Operating System :: OS Independent
Requires-Dist: dask (>=0.17.1)
Requires-Dist: matplotlib (>=2.2.2)
Requires-Dist: bokeh (>=0.12.13)
Requires-Dist: netcdf4 (>=1.3.1)
Requires-Dist: numpy (>=1.13.3)
Requires-Dist: pandas (>=0.22.0)
Requires-Dist: pytest (>=3.5.0)
Requires-Dist: xarray (>=0.10.7)
Requires-Dist: bottleneck (>=1.2.1)
Requires-Dist: cartopy (>=0.16.0)
Requires-Dist: scipy (>=1.0.0)
Requires-Dist: pyspharm (>=1.0.9)
Requires-Dist: windspharm (>=1.6.0)
